dirmapper_core/__init__.py
dirmapper_core/ai/README.md
dirmapper_core/ai/__init__.py
dirmapper_core/ai/content_generator.py
dirmapper_core/ai/content_service.py
dirmapper_core/ai/summarizer.py
dirmapper_core/data/.mapping-ignore
dirmapper_core/formatter/__init__.py
dirmapper_core/formatter/base_formatter.py
dirmapper_core/formatter/format_instruction.py
dirmapper_core/formatter/formatter.py
dirmapper_core/generator/__init__.py
dirmapper_core/generator/directory_structure_generator.py
dirmapper_core/ignore/__init__.py
dirmapper_core/ignore/ignore_list_reader.py
dirmapper_core/ignore/path_ignorer.py
dirmapper_core/models/directory_item.py
dirmapper_core/models/directory_structure.py
dirmapper_core/sort/__init__.py
dirmapper_core/sort/sorting_strategy.py
dirmapper_core/styles/__init__.py
dirmapper_core/styles/base_style.py
dirmapper_core/styles/flat_list_style.py
dirmapper_core/styles/html_style.py
dirmapper_core/styles/indentation_style.py
dirmapper_core/styles/json_style.py
dirmapper_core/styles/list_style.py
dirmapper_core/styles/tree_style.py
dirmapper_core/utils/__init__.py
dirmapper_core/utils/cache.py
dirmapper_core/utils/cache_manager.py
dirmapper_core/utils/constants.py
dirmapper_core/utils/logger.py
dirmapper_core/utils/paginator.py
dirmapper_core/utils/text_analyzer.py
dirmapper_core/utils/utils.py
dirmapper_core/writer/__init__.py
dirmapper_core/writer/structure_writer.py
dirmapper_core/writer/template_parser.py
dirmapper_core/writer/template_writer.py
dirmapper_core-0.2.4.dist-info/LICENSE
dirmapper_core-0.2.4.dist-info/METADATA
dirmapper_core-0.2.4.dist-info/WHEEL
dirmapper_core-0.2.4.dist-info/top_level.txt
dirmapper_core-0.2.4.dist-info/RECORD
