Metadata-Version: 2.1
Name: dirmapper-core
Version: 0.2.4
Summary: Core library for directory mapping and summarization
Author-email: Nash Dean <nashdean.github@gmail.com>
License: MIT License
Project-URL: Source, https://github.com/nashdean/dirmapper-core
Project-URL: Changelog, https://github.com/nashdean/dirmapper-core/blob/master/CHANGELOG.md
Project-URL: Issues, https://github.com/nashdean/dirmapper-core/issues
Keywords: directory,mapping,summarization
Classifier: Programming Language :: Python :: 3
Classifier: License :: OSI Approved :: MIT License
Classifier: Operating System :: OS Independent
Classifier: Development Status :: 4 - Beta
Classifier: Intended Audience :: Developers
Classifier: Topic :: Software Development :: Libraries :: Python Modules
Requires-Python: >=3.10
License-File: LICENSE
Requires-Dist: requests
Requires-Dist: openai
Requires-Dist: pydantic
Requires-Dist: pyyaml
Requires-Dist: typing-extensions
